puppet/__init__.py
puppet/core.py
puppet/datasets/__init__.py
puppet/datasets/creator.py
puppet_ai-0.1.0.dist-info/METADATA
puppet_ai-0.1.0.dist-info/WHEEL
puppet_ai-0.1.0.dist-info/top_level.txt
puppet_ai-0.1.0.dist-info/RECORD
